soma/__init__.py
soma/estilo/__init__.py
soma/estilo/modelling.py
soma/estilo/utils.py
soma_teste-0.1.dev38.dist-info/METADATA
soma_teste-0.1.dev38.dist-info/WHEEL
soma_teste-0.1.dev38.dist-info/top_level.txt
soma_teste-0.1.dev38.dist-info/RECORD
