Metadata-Version: 2.1
Name: soma-teste
Version: 0.1.dev38
Summary: Private utility package used by SomaLabs.
Home-page: https://bitbucket.org/somalabs/soma-tools
Author: Cyfer
Author-email: luiz.costa@somagrupo.com.br
License: UNKNOWN
Platform: UNKNOWN
Classifier: Programming Language :: Python :: 3
Classifier: License :: OSI Approved :: MIT License
Classifier: Operating System :: OS Independent
Requires-Dist: pandas
Requires-Dist: mysql-connector
